{"data":{"user":{"name":"Tommaso Patriti","bio":"","avatarUrl":"https://avatars.githubusercontent.com/u/14377433?u=9b8d87ede3f9626b1e4af5c840b986e04729f029&v=4","location":"Italy","pinnedItems":{"totalCount":4,"edges":[{"node":{"name":"OOP20-Jhaturanga","description":"An advanced chess game in Java","forkCount":9,"stargazers":{"totalCount":10},"url":"https://github.com/zucchero-sintattico/OOP20-Jhaturanga","id":"MDEwOlJlcG9zaXRvcnkzMjI4OTc1ODA=","diskUsage":69114,"primaryLanguage":{"name":"Java","color":"#b07219"}}},{"node":{"name":"HYC","description":"Progetto per Tecnologie Web","forkCount":0,"stargazers":{"totalCount":3},"url":"https://github.com/zucchero-sintattico/HYC","id":"R_kgDOGZjRPg","diskUsage":8342,"primaryLanguage":{"name":"PHP","color":"#4F5D95"}}},{"node":{"name":"piperchat","description":"A microservices chat app","forkCount":0,"stargazers":{"totalCount":11},"url":"https://github.com/zucchero-sintattico/piperchat","id":"R_kgDOJHAqiw","diskUsage":13306,"primaryLanguage":{"name":"TypeScript","color":"#3178c6"}}},{"node":{"name":"piper-kt","description":"A microservices chat app, kotlin based.","forkCount":0,"stargazers":{"totalCount":10},"url":"https://github.com/zucchero-sintattico/piper-kt","id":"R_kgDOLOIJ4A","diskUsage":13866,"primaryLanguage":{"name":"Kotlin","color":"#A97BFF"}}}]}}}}